pingertron/__init__.py
pingertron/main.py
pingertron/metrics.py
pingertron/probes.py
pingertron/probes_config.py
pingertron-0.3.0.dist-info/LICENSE
pingertron-0.3.0.dist-info/METADATA
pingertron-0.3.0.dist-info/WHEEL
pingertron-0.3.0.dist-info/entry_points.txt
pingertron-0.3.0.dist-info/RECORD
