Metadata-Version: 2.1
Name: pingertron
Version: 0.3.0
Summary: Ping Hosts and URLs and keep stats on successes and failures
Home-page: https://github.com/micktwomey/pingertron
License: MIT
Author: Michael Twomey
Author-email: mick@twomeylee.name
Requires-Python: >=3.11,<4.0
Classifier: License :: OSI Approved :: MIT License
Classifier: Programming Language :: Python :: 3
Classifier: Programming Language :: Python :: 3.11
Requires-Dist: httpx (>=0.24.0,<0.25.0)
Requires-Dist: icmplib (>=3.0.3,<4.0.0)
Requires-Dist: prometheus-client (>=0.16.0,<0.17.0)
Requires-Dist: psutil (>=5.9.5,<6.0.0)
Requires-Dist: pydantic (>=1.10.7,<2.0.0)
Requires-Dist: pydantic-yaml (>=1.0.0a2,<2.0.0)
Requires-Dist: rich (>=13.3.5,<14.0.0)
Requires-Dist: structlog (>=23.1.0,<24.0.0)
Requires-Dist: typer (>=0.9.0,<0.10.0)
Project-URL: Repository, https://github.com/micktwomey/pingertron
